conson_xp-2.0.4.dist-info/METADATA
conson_xp-2.0.4.dist-info/WHEEL
conson_xp-2.0.4.dist-info/entry_points.txt
conson_xp-2.0.4.dist-info/licenses/LICENSE
xp/__init__.py
xp/cli/__init__.py
xp/cli/__main__.py
xp/cli/commands/__init__.py
xp/cli/commands/conbus/__init__.py
xp/cli/commands/conbus/conbus.py
xp/cli/commands/conbus/conbus_actiontable_commands.py
xp/cli/commands/conbus/conbus_autoreport_commands.py
xp/cli/commands/conbus/conbus_blink_commands.py
xp/cli/commands/conbus/conbus_config_commands.py
xp/cli/commands/conbus/conbus_custom_commands.py
xp/cli/commands/conbus/conbus_datapoint_commands.py
xp/cli/commands/conbus/conbus_discover_commands.py
xp/cli/commands/conbus/conbus_event_commands.py
xp/cli/commands/conbus/conbus_export_commands.py
xp/cli/commands/conbus/conbus_lightlevel_commands.py
xp/cli/commands/conbus/conbus_linknumber_commands.py
xp/cli/commands/conbus/conbus_modulenumber_commands.py
xp/cli/commands/conbus/conbus_msactiontable_commands.py
xp/cli/commands/conbus/conbus_output_commands.py
xp/cli/commands/conbus/conbus_raw_commands.py
xp/cli/commands/conbus/conbus_receive_commands.py
xp/cli/commands/conbus/conbus_scan_commands.py
xp/cli/commands/file_commands.py
xp/cli/commands/module_commands.py
xp/cli/commands/reverse_proxy_commands.py
xp/cli/commands/server/__init__.py
xp/cli/commands/server/server_commands.py
xp/cli/commands/telegram/__init__.py
xp/cli/commands/telegram/telegram.py
xp/cli/commands/telegram/telegram_blink_commands.py
xp/cli/commands/telegram/telegram_checksum_commands.py
xp/cli/commands/telegram/telegram_discover_commands.py
xp/cli/commands/telegram/telegram_linknumber_commands.py
xp/cli/commands/telegram/telegram_parse_commands.py
xp/cli/commands/telegram/telegram_version_commands.py
xp/cli/commands/term/__init__.py
xp/cli/commands/term/term.py
xp/cli/commands/term/term_commands.py
xp/cli/main.py
xp/cli/utils/__init__.py
xp/cli/utils/click_tree.py
xp/cli/utils/datapoint_type_choice.py
xp/cli/utils/decorators.py
xp/cli/utils/error_handlers.py
xp/cli/utils/formatters.py
xp/cli/utils/module_type_choice.py
xp/cli/utils/serial_number_type.py
xp/cli/utils/system_function_choice.py
conson_xp-2.0.4.dist-info/RECORD
