Metadata-Version: 2.1
Name: conson-xp
Version: 2.0.4
Summary: XP Protocol Communication Tools
Author-Email: ldvchosal <ldvchosal@github.com>
License: MIT License
Project-URL: Homepage, https://github.com/lduchosal/xp
Project-URL: Bug Reports, https://github.com/lduchosal/xp/issues
Project-URL: Source, https://github.com/lduchosal/xp
Requires-Python: >=3.11
Requires-Dist: click>=8.3
Requires-Dist: click-help-colors>=0.9
Requires-Dist: pyyaml>=6.0
Requires-Dist: structlog>=22.0
Requires-Dist: fastapi>=0.118
Requires-Dist: uvicorn>=0.37
Requires-Dist: pydantic>=2.11
Requires-Dist: HAP-python[QRCode]>=5.0.0
Requires-Dist: punq>=0.7.0
Requires-Dist: twisted>=25.5.0
Requires-Dist: psygnal>=0.15.0
Requires-Dist: textual>=1.0.0
Requires-Dist: python-statemachine>=2.5.0
